odoo/addons/report_pdf_zip_download/README.rst
odoo/addons/report_pdf_zip_download/__init__.py
odoo/addons/report_pdf_zip_download/__manifest__.py
odoo/addons/report_pdf_zip_download/controllers/__init__.py
odoo/addons/report_pdf_zip_download/controllers/main.py
odoo/addons/report_pdf_zip_download/i18n/it.po
odoo/addons/report_pdf_zip_download/i18n/report_pdf_zip_download.pot
odoo/addons/report_pdf_zip_download/models/__init__.py
odoo/addons/report_pdf_zip_download/models/ir_actions_report.py
odoo/addons/report_pdf_zip_download/readme/CONFIGURE.md
odoo/addons/report_pdf_zip_download/readme/CONTRIBUTORS.md
odoo/addons/report_pdf_zip_download/readme/DESCRIPTION.md
odoo/addons/report_pdf_zip_download/static/description/icon.png
odoo/addons/report_pdf_zip_download/static/description/index.html
odoo/addons/report_pdf_zip_download/static/src/js/action_manager_report.esm.js
odoo/addons/report_pdf_zip_download/views/ir_actions_report_views.xml
odoo_addon_report_pdf_zip_download-18.0.1.0.0.6.dist-info/METADATA
odoo_addon_report_pdf_zip_download-18.0.1.0.0.6.dist-info/WHEEL
odoo_addon_report_pdf_zip_download-18.0.1.0.0.6.dist-info/top_level.txt
odoo_addon_report_pdf_zip_download-18.0.1.0.0.6.dist-info/RECORD
